xarray_pschdf5/__init__.py
xarray_pschdf5/_core.pyi
xarray_pschdf5/_version.py
xarray_pschdf5/_version.pyi
xarray_pschdf5/pschdf5_backend.py
xarray_pschdf5/py.typed
xarray_pschdf5/sample/sample_xdmf.iof.004020.xdmf
xarray_pschdf5/sample/sample_xdmf.iof.004020_p000000.h5
xarray_pschdf5/sample/sample_xdmf.iof.004040.xdmf
xarray_pschdf5/sample/sample_xdmf.iof.xdmf
xarray_pschdf5-0.0.1a0.dist-info/licenses/LICENSE
xarray_pschdf5-0.0.1a0.dist-info/METADATA
xarray_pschdf5-0.0.1a0.dist-info/WHEEL
xarray_pschdf5-0.0.1a0.dist-info/entry_points.txt
xarray_pschdf5-0.0.1a0.dist-info/top_level.txt
xarray_pschdf5-0.0.1a0.dist-info/RECORD
