Metadata-Version: 2.4
Name: xarray-pschdf5
Version: 0.0.1a0
Summary: XArray reader for PSC HDF5 data
Author-email: Kai Germaschewski <kai.germaschewski@gmail.com>
License: BSD 3-Clause License
Project-URL: Homepage, https://github.com/psc-code/xarray-pschdf5
Project-URL: Bug Tracker, https://github.com/psc-code/xarray-pschdf5/issues
Project-URL: Discussions, https://github.com/psc-code/xarray-pschdf5/discussions
Project-URL: Changelog, https://github.com/psc-code/xarray-pschdf5/releases
Classifier: Development Status :: 1 - Planning
Classifier: Intended Audience :: Science/Research
Classifier: Intended Audience :: Developers
Classifier: License :: OSI Approved :: Apache Software License
Classifier: Operating System :: OS Independent
Classifier: Programming Language :: Python
Classifier: Programming Language :: Python :: 3
Classifier: Programming Language :: Python :: 3 :: Only
Classifier: Programming Language :: Python :: 3.10
Classifier: Programming Language :: Python :: 3.11
Classifier: Programming Language :: Python :: 3.12
Classifier: Programming Language :: Python :: 3.13
Classifier: Topic :: Scientific/Engineering
Classifier: Typing :: Typed
Requires-Python: >=3.10
License-File: LICENSE
Requires-Dist: pugixml>=0.5.0
Requires-Dist: h5py
Requires-Dist: xarray
Requires-Dist: typing-extensions
Provides-Extra: test
Requires-Dist: pytest>=6; extra == "test"
Requires-Dist: pytest-cov>=3; extra == "test"
Requires-Dist: typing-extensions; extra == "test"
Provides-Extra: dev
Requires-Dist: pytest>=6; extra == "dev"
Requires-Dist: pytest-cov>=3; extra == "dev"
Requires-Dist: typing-extensions; extra == "dev"
Provides-Extra: docs
Requires-Dist: sphinx>=7.0; extra == "docs"
Requires-Dist: myst_parser>=0.13; extra == "docs"
Requires-Dist: sphinx_copybutton; extra == "docs"
Requires-Dist: sphinx_autodoc_typehints; extra == "docs"
Requires-Dist: furo>=2023.08.17; extra == "docs"
Dynamic: license-file
